{
  "content": [
    {
      "seasoning": {},
      "image": "https://i1.douguo.com//upload/caiku/a/1/8/600_a124a28b90d12b51c3c0c134045e64d8.jpg",
      "major": [
        {
          "note": "200克",
          "title": "牛里脊"
        },
        {
          "note": "1个",
          "title": "杏鲍菇"
        },
        {
          "note": "1勺",
          "title": "料酒"
        },
        {
          "note": "2勺",
          "title": "生抽"
        },
        {
          "note": "1小勺",
          "title": "黑胡椒粉"
        },
        {
          "note": "1勺",
          "title": "玉米淀粉"
        },
        {
          "note": "适量",
          "title": "油"
        },
        {
          "note": "1个",
          "title": "青椒"
        },
        {
          "note": "少许",
          "title": "盐"
        },
        {
          "note": "1勺",
          "title": "蚝油"
        }
      ],
      "cook_rate": 0,
      "dish": "杏鲍菇牛肉粒",
      "cookstep": [
        {
          "image": "https://cp1.douguo.com/upload/caiku/f/0/9/600_f0a656c2f4cc181c576234e01b1de5e9.jpg",
          "thumb": "https://cp1.douguo.com/upload/caiku/f/0/9/140_f0a656c2f4cc181c576234e01b1de5e9.jpg",
          "position": 1,
          "content": "杏鲍菇切2厘米见方的块，青椒切块。"
        },
        {
          "image": "https://cp1.douguo.com/upload/caiku/f/7/1/600_f7d78500ba40e9ca8f7e9df7c7f07e51.jpg",
          "thumb": "https://cp1.douguo.com/upload/caiku/f/7/1/140_f7d78500ba40e9ca8f7e9df7c7f07e51.jpg",
          "position": 2,
          "content": "牛里脊切2厘米方的小块，加料酒、1勺黑胡椒粉、淀粉、1勺生抽抓匀，腌制10分钟。"
        },
        {
          "image": "https://cp1.douguo.com/upload/caiku/e/6/b/600_e645b16ab217fe0e2a84c487f613891b.jpg",
          "thumb": "https://cp1.douguo.com/upload/caiku/e/6/b/140_e645b16ab217fe0e2a84c487f613891b.jpg",
          "position": 3,
          "content": "油热下牛肉粒翻炒变色就盛起来。"
        },
        {
          "image": "https://cp1.douguo.com/upload/caiku/e/6/9/600_e66bcbfce225b2dcd08bf8d2437e7989.jpg",
          "thumb": "https://cp1.douguo.com/upload/caiku/e/6/9/140_e66bcbfce225b2dcd08bf8d2437e7989.jpg",
          "position": 4,
          "content": "油锅下杏鲍菇，翻炒到几面变色。"
        },
        {
          "image": "https://cp1.douguo.com/upload/caiku/7/0/5/600_704dae234108dc07b5593e1babdf1275.jpg",
          "thumb": "https://cp1.douguo.com/upload/caiku/7/0/5/140_704dae234108dc07b5593e1babdf1275.jpg",
          "position": 5,
          "content": "倒入牛肉粒和青椒。"
        },
        {
          "image": "https://cp1.douguo.com/upload/caiku/5/b/1/600_5b03dc0cbcfad0f6c8fb41a72a79bd91.jpg",
          "thumb": "https://cp1.douguo.com/upload/caiku/5/b/1/140_5b03dc0cbcfad0f6c8fb41a72a79bd91.jpg",
          "position": 6,
          "content": "加入剩余调味料，加少许水、适量盐，翻炒熟。"
        }
      ]
    },
    {
      "seasoning": {},
      "image": "https://i1.douguo.com//upload/caiku/5/0/8/600_506b0e84c7886d24efd6548a0c6f8eb8.jpeg",
      "major": [
        {
          "note": "4个",
          "title": "番茄"
        },
        {
          "note": "2个",
          "title": "土豆"
        },
        {
          "note": "450克",
          "title": "牛肉"
        },
        {
          "note": "可不加",
          "title": "番茄酱"
        },
        {
          "note": "适量",
          "title": "葱姜"
        },
        {
          "note": "1勺",
          "title": "太太乐宴会料酒"
        },
        {
          "note": "6克",
          "title": "盐"
        },
        {
          "note": "1勺",
          "title": "白糖"
        },
        {
          "note": "1勺",
          "title": "番茄酱"
        }
      ],
      "cook_rate": 0,
      "dish": "番茄土豆炖牛肉",
      "cookstep": [
        {
          "image": "https://cp1.douguo.com/upload/caiku/c/f/9/600_cfc16f1020ed6a02c63dc3eb2be97ed9.jpeg",
          "thumb": "https://cp1.douguo.com/upload/caiku/c/f/9/140_cfc16f1020ed6a02c63dc3eb2be97ed9.jpeg",
          "position": 1,
          "content": "牛肉切大块洗净备用"
        },
        {
          "image": "https://cp1.douguo.com/upload/caiku/1/a/c/600_1a39921c6b8bfbe1642dfc3ffc404c7c.jpeg",
          "thumb": "https://cp1.douguo.com/upload/caiku/1/a/c/140_1a39921c6b8bfbe1642dfc3ffc404c7c.jpeg",
          "position": 2,
          "content": "牛肉放高压锅，加入葱姜八角桂皮香叶，番茄酱"
        },
        {
          "image": "https://cp1.douguo.com/upload/caiku/8/9/a/600_89c26e455d3d5c868921eba181a2f0aa.jpeg",
          "thumb": "https://cp1.douguo.com/upload/caiku/8/9/a/140_89c26e455d3d5c868921eba181a2f0aa.jpeg",
          "position": 3,
          "content": "加入一大勺太太乐宴会料酒去腥增香"
        },
        {
          "image": "https://cp1.douguo.com/upload/caiku/9/3/d/600_9347bbb552b73a4de33b540aa00d160d.jpeg",
          "thumb": "https://cp1.douguo.com/upload/caiku/9/3/d/140_9347bbb552b73a4de33b540aa00d160d.jpeg",
          "position": 4,
          "content": "加入适量水，高压锅炖煮30分钟至牛肉熟烂"
        },
        {
          "image": "https://cp1.douguo.com/upload/caiku/d/1/2/600_d1889ac6aa093434d1d14215390c8172.jpeg",
          "thumb": "https://cp1.douguo.com/upload/caiku/d/1/2/140_d1889ac6aa093434d1d14215390c8172.jpeg",
          "position": 5,
          "content": "起锅烧油，放入番茄土豆块翻炒均匀"
        },
        {
          "image": "https://cp1.douguo.com/upload/caiku/7/c/a/600_7c0384e3341d917cceb6a296fa438c6a.jpeg",
          "thumb": "https://cp1.douguo.com/upload/caiku/7/c/a/140_7c0384e3341d917cceb6a296fa438c6a.jpeg",
          "position": 6,
          "content": "加入一勺盐一勺白糖调味"
        },
        {
          "image": "https://cp1.douguo.com/upload/caiku/c/3/b/600_c34b3fa7be312aed5adab4db0286d9bb.jpeg",
          "thumb": "https://cp1.douguo.com/upload/caiku/c/3/b/140_c34b3fa7be312aed5adab4db0286d9bb.jpeg",
          "position": 7,
          "content": "加入牛肉和汤"
        },
        {
          "image": "https://cp1.douguo.com/upload/caiku/2/c/c/600_2c5d2e0ce68bf60e6b7059549985763c.jpeg",
          "thumb": "https://cp1.douguo.com/upload/caiku/2/c/c/140_2c5d2e0ce68bf60e6b7059549985763c.jpeg",
          "position": 8,
          "content": "再炖煮至牛肉熟透即可"
        },
        {
          "image": "https://cp1.douguo.com/upload/caiku/e/8/1/600_e814196035216b86e40a254c2e59a651.jpeg",
          "thumb": "https://cp1.douguo.com/upload/caiku/e/8/1/140_e814196035216b86e40a254c2e59a651.jpeg",
          "position": 9,
          "content": "撒葱花装盘食用"
        },
        {
          "image": "https://cp1.douguo.com/upload/caiku/f/2/1/600_f2cf8ded40f733802bf220467c7b8661.jpeg",
          "thumb": "https://cp1.douguo.com/upload/caiku/f/2/1/140_f2cf8ded40f733802bf220467c7b8661.jpeg",
          "position": 10,
          "content": "成品图"
        }
      ]
    },
    {
      "seasoning": {},
      "image": "https://i1.douguo.com//upload/caiku/9/d/7/600_9d9963cd1c3431a66630102ecff028d7.jpeg",
      "major": [
        {
          "note": "半斤",
          "title": "黄牛肉"
        },
        {
          "note": "适量多",
          "title": "香菜"
        },
        {
          "note": "3勺",
          "title": "剁椒"
        },
        {
          "note": "适量",
          "title": "姜丝"
        },
        {
          "note": "1勺",
          "title": "淀粉"
        },
        {
          "note": "2勺",
          "title": "生抽（腌制牛肉的量）"
        },
        {
          "note": "2茶匙",
          "title": "蒜末"
        },
        {
          "note": "适量",
          "title": "葱段"
        },
        {
          "note": "1个",
          "title": "尖椒"
        },
        {
          "note": "1勺",
          "title": "耗油"
        },
        {
          "note": "适量",
          "title": "生抽"
        },
        {
          "note": "少量",
          "title": "盐"
        }
      ],
      "cook_rate": 5,
      "dish": "米饭终结者~小炒黄牛肉",
      "cookstep": [
        {
          "image": "https://cp1.douguo.com/upload/caiku/b/1/6/600_b1a010abfa23ad1622a948d413a9b4d6.jpeg",
          "thumb": "https://cp1.douguo.com/upload/caiku/b/1/6/140_b1a010abfa23ad1622a948d413a9b4d6.jpeg",
          "position": 1,
          "content": "牛肉切成小条，比肉片好入味。为了更好吃，不要偷懒呀"
        },
        {
          "image": "https://cp1.douguo.com/upload/caiku/8/b/f/600_8b852ff4275cf0137b2020e2e2b38a1f.jpeg",
          "thumb": "https://cp1.douguo.com/upload/caiku/8/b/f/140_8b852ff4275cf0137b2020e2e2b38a1f.jpeg",
          "position": 2,
          "content": "放入淀粉和适量生抽，用手抓匀腌制20min。"
        },
        {
          "image": "https://cp1.douguo.com/upload/caiku/f/f/3/600_ff6a6a06d0ef4865f71d61fbcaee05e3.jpeg",
          "thumb": "https://cp1.douguo.com/upload/caiku/f/f/3/140_ff6a6a06d0ef4865f71d61fbcaee05e3.jpeg",
          "position": 3,
          "content": "放在一旁备用"
        },
        {
          "image": "https://cp1.douguo.com/upload/caiku/1/a/a/600_1a774a568542ab50d4678a5892b26d3a.jpeg",
          "thumb": "https://cp1.douguo.com/upload/caiku/1/a/a/140_1a774a568542ab50d4678a5892b26d3a.jpeg",
          "position": 4,
          "content": "锅热后倒油"
        },
        {
          "image": "https://cp1.douguo.com/upload/caiku/a/6/4/600_a6354a02cfe95f75497e34da3c3e1604.jpeg",
          "thumb": "https://cp1.douguo.com/upload/caiku/a/6/4/140_a6354a02cfe95f75497e34da3c3e1604.jpeg",
          "position": 5,
          "content": "加入腌制好的牛肉，别让牛肉混成一坨一坨的。"
        },
        {
          "image": "https://cp1.douguo.com/upload/caiku/e/6/5/600_e654e776a328f3b578dd3bef9a0d3b55.jpeg",
          "thumb": "https://cp1.douguo.com/upload/caiku/e/6/5/140_e654e776a328f3b578dd3bef9a0d3b55.jpeg",
          "position": 6,
          "content": "炒制微微变色盛出，炒的太久口感会老"
        },
        {
          "image": "https://cp1.douguo.com/upload/caiku/0/d/8/600_0d3ff7b5b0cac180fd82c6deddf5feb8.jpeg",
          "thumb": "https://cp1.douguo.com/upload/caiku/0/d/8/140_0d3ff7b5b0cac180fd82c6deddf5feb8.jpeg",
          "position": 7,
          "content": "重新起锅加入葱姜蒜小红椒"
        },
        {
          "image": "https://cp1.douguo.com/upload/caiku/d/e/3/600_de46aff21e5af047b4ad5b0470106eb3.jpeg",
          "thumb": "https://cp1.douguo.com/upload/caiku/d/e/3/140_de46aff21e5af047b4ad5b0470106eb3.jpeg",
          "position": 8,
          "content": "炒出香味后加入尖椒段和香菜根"
        },
        {
          "image": "https://cp1.douguo.com/upload/caiku/d/2/1/600_d26d82fe8968e55f96980c1756a26091.jpeg",
          "thumb": "https://cp1.douguo.com/upload/caiku/d/2/1/140_d26d82fe8968e55f96980c1756a26091.jpeg",
          "position": 9,
          "content": "准备加入刚才炒好的牛肉"
        },
        {
          "image": "https://cp1.douguo.com/upload/caiku/3/b/f/600_3b717a8199339d5a368822299b5087af.jpeg",
          "thumb": "https://cp1.douguo.com/upload/caiku/3/b/f/140_3b717a8199339d5a368822299b5087af.jpeg",
          "position": 10,
          "content": "放入这道菜的灵魂，湖南剁椒"
        },
        {
          "image": "https://cp1.douguo.com/upload/caiku/9/9/7/600_995d60d4df93c0d9f0365d3686da16d7.jpeg",
          "thumb": "https://cp1.douguo.com/upload/caiku/9/9/7/140_995d60d4df93c0d9f0365d3686da16d7.jpeg",
          "position": 11,
          "content": "大火翻炒拨拉~"
        },
        {
          "image": "https://cp1.douguo.com/upload/caiku/d/e/e/600_deeb6d0338af8419a8aabf2bb4c8525e.jpeg",
          "thumb": "https://cp1.douguo.com/upload/caiku/d/e/e/140_deeb6d0338af8419a8aabf2bb4c8525e.jpeg",
          "position": 12,
          "content": "快出锅关火前，加入香菜末快速翻炒后就可以出锅了"
        },
        {
          "image": "https://cp1.douguo.com/upload/caiku/9/4/2/600_9429f30065114f4c7a552affbd8f2962.jpeg",
          "thumb": "https://cp1.douguo.com/upload/caiku/9/4/2/140_9429f30065114f4c7a552affbd8f2962.jpeg",
          "position": 13,
          "content": "盛出摆盘，美味扑鼻而来"
        },
        {
          "image": "https://cp1.douguo.com/upload/caiku/b/6/e/600_b69bca81c05a7b4333b92a639697496e.jpeg",
          "thumb": "https://cp1.douguo.com/upload/caiku/b/6/e/140_b69bca81c05a7b4333b92a639697496e.jpeg",
          "position": 14,
          "content": "米饭终结者"
        }
      ]
    },
    {
      "seasoning": {},
      "image": "https://i1.douguo.com//upload/caiku/4/d/3/600_4d120ce32e8758cc4d9c70ad5f637aa3.jpeg",
      "major": [
        {
          "note": "200克",
          "title": "牛肉"
        },
        {
          "note": "1小块",
          "title": "冬瓜"
        },
        {
          "note": "2根",
          "title": "小葱"
        },
        {
          "note": "1个",
          "title": "独蒜"
        },
        {
          "note": "1块",
          "title": "老姜"
        },
        {
          "note": "2克",
          "title": "盐"
        },
        {
          "note": "1克",
          "title": "味精"
        },
        {
          "note": "适量",
          "title": "黑胡椒粉"
        },
        {
          "note": "少许",
          "title": "生抽"
        },
        {
          "note": "1茶匙",
          "title": "淀粉"
        },
        {
          "note": "50ml",
          "title": "温开水"
        }
      ],
      "cook_rate": 5,
      "dish": "牛肉丸子汤",
      "cookstep": [
        {
          "image": "https://cp1.douguo.com/upload/caiku/8/a/b/600_8a34a1f09ec5a4be27b83d577b12c0fb.jpeg",
          "thumb": "https://cp1.douguo.com/upload/caiku/8/a/b/140_8a34a1f09ec5a4be27b83d577b12c0fb.jpeg",
          "position": 1,
          "content": "姜蒜切片、小葱切段，加入50毫升温开水泡10分钟。"
        },
        {
          "image": "https://cp1.douguo.com/upload/caiku/3/d/6/600_3dab2d71a02e2374d7d15ef3995e5fb6.jpeg",
          "thumb": "https://cp1.douguo.com/upload/caiku/3/d/6/140_3dab2d71a02e2374d7d15ef3995e5fb6.jpeg",
          "position": 2,
          "content": "牛肉200克。"
        },
        {
          "image": "https://cp1.douguo.com/upload/caiku/7/b/7/600_7bcb67e46c26969a60a6f51ba57211e7.jpeg",
          "thumb": "https://cp1.douguo.com/upload/caiku/7/b/7/140_7bcb67e46c26969a60a6f51ba57211e7.jpeg",
          "position": 3,
          "content": "剁碎。"
        },
        {
          "image": "https://cp1.douguo.com/upload/caiku/a/7/0/600_a720f54595fd5d0f1dc77dadbb235030.jpeg",
          "thumb": "https://cp1.douguo.com/upload/caiku/a/7/0/140_a720f54595fd5d0f1dc77dadbb235030.jpeg",
          "position": 4,
          "content": "加入盐、味精、黑胡椒粉、生抽、淀粉、姜蒜水。"
        },
        {
          "image": "https://cp1.douguo.com/upload/caiku/0/4/1/600_04841730a6e89f2e98e1aff7fa183e11.jpeg",
          "thumb": "https://cp1.douguo.com/upload/caiku/0/4/1/140_04841730a6e89f2e98e1aff7fa183e11.jpeg",
          "position": 5,
          "content": "搅拌均匀。"
        },
        {
          "image": "https://cp1.douguo.com/upload/caiku/3/a/3/600_3a5b7d1c01342d0159df11d2618762b3.jpeg",
          "thumb": "https://cp1.douguo.com/upload/caiku/3/a/3/140_3a5b7d1c01342d0159df11d2618762b3.jpeg",
          "position": 6,
          "content": "用机器搅打成肉泥。"
        },
        {
          "image": "https://cp1.douguo.com/upload/caiku/e/6/e/600_e64d11a92d9522c7fd9c568685d3593e.jpeg",
          "thumb": "https://cp1.douguo.com/upload/caiku/e/6/e/140_e64d11a92d9522c7fd9c568685d3593e.jpeg",
          "position": 7,
          "content": "这样就OK了！\n因为我用的绞肉机比较小，所以是先把牛肉剁碎再搅打成泥，如果用的机器比较大，可以把前面四个步骤一起完成。"
        },
        {
          "image": "https://cp1.douguo.com/upload/caiku/6/8/2/600_689ddb2fdec46413fd23236293ff06b2.jpeg",
          "thumb": "https://cp1.douguo.com/upload/caiku/6/8/2/140_689ddb2fdec46413fd23236293ff06b2.jpeg",
          "position": 8,
          "content": "冬瓜去皮洗干净，切成厚片。"
        },
        {
          "image": "https://cp1.douguo.com/upload/caiku/3/c/1/600_3c70ea6ed6f2a678a14a2f2bc78f1da1.jpeg",
          "thumb": "https://cp1.douguo.com/upload/caiku/3/c/1/140_3c70ea6ed6f2a678a14a2f2bc78f1da1.jpeg",
          "position": 9,
          "content": "加适量清水煮软。"
        },
        {
          "image": "https://cp1.douguo.com/upload/caiku/8/c/9/600_8c92fbe12d6da9a82440ef06a92276b9.jpeg",
          "thumb": "https://cp1.douguo.com/upload/caiku/8/c/9/140_8c92fbe12d6da9a82440ef06a92276b9.jpeg",
          "position": 10,
          "content": "手挤丸子，超级好玩儿！"
        },
        {
          "image": "https://cp1.douguo.com/upload/caiku/6/0/b/600_60de0e7b7ad249ab4b1757d098e811bb.jpeg",
          "thumb": "https://cp1.douguo.com/upload/caiku/6/0/b/140_60de0e7b7ad249ab4b1757d098e811bb.jpeg",
          "position": 11,
          "content": "加入丸子煮8分钟。"
        },
        {
          "image": "https://cp1.douguo.com/upload/caiku/f/b/6/600_fb9bec314567c882b8b803ca49d66486.jpeg",
          "thumb": "https://cp1.douguo.com/upload/caiku/f/b/6/140_fb9bec314567c882b8b803ca49d66486.jpeg",
          "position": 12,
          "content": "汤里加入1克盐调味。"
        },
        {
          "image": "https://cp1.douguo.com/upload/caiku/d/c/8/600_dc96211c0a83d20414e4a51667a23ef8.jpeg",
          "thumb": "https://cp1.douguo.com/upload/caiku/d/c/8/140_dc96211c0a83d20414e4a51667a23ef8.jpeg",
          "position": 13,
          "content": "起锅撒上葱花即可。"
        },
        {
          "image": "https://cp1.douguo.com/upload/caiku/a/7/9/600_a73017a83c3caaac0e8d72c85f6c35d9.jpeg",
          "thumb": "https://cp1.douguo.com/upload/caiku/a/7/9/140_a73017a83c3caaac0e8d72c85f6c35d9.jpeg",
          "position": 14,
          "content": "赶紧试试吧！"
        }
      ]
    },
    {
      "seasoning": {},
      "image": "https://i1.douguo.com//upload/caiku/8/a/7/600_8a847c4fbad01785674a53f70c8aa5b7.jpg",
      "major": [
        {
          "note": "150克",
          "title": "牛里脊"
        },
        {
          "note": "1勺",
          "title": "料酒"
        },
        {
          "note": "2勺",
          "title": "生抽"
        },
        {
          "note": "2勺",
          "title": "淀粉"
        },
        {
          "note": "半个",
          "title": "洋葱"
        },
        {
          "note": "3根",
          "title": "香菜"
        },
        {
          "note": "3个",
          "title": "小米辣"
        },
        {
          "note": "3片",
          "title": "姜"
        },
        {
          "note": "1克",
          "title": "盐"
        },
        {
          "note": "1小勺",
          "title": "鸡精"
        }
      ],
      "cook_rate": 5,
      "dish": "牛气冲天之小炒牛肉",
      "cookstep": [
        {
          "image": "https://cp1.douguo.com/upload/caiku/7/9/3/600_79175d091be962fe3a46ffaaade17653.jpg",
          "thumb": "https://cp1.douguo.com/upload/caiku/7/9/3/140_79175d091be962fe3a46ffaaade17653.jpg",
          "position": 1,
          "content": "备好食材，牛里脊切薄片，香菜切的长一些"
        },
        {
          "image": "https://cp1.douguo.com/upload/caiku/f/d/f/600_fd8734de2981388eb5cf69c80c1af7df.jpg",
          "thumb": "https://cp1.douguo.com/upload/caiku/f/d/f/140_fd8734de2981388eb5cf69c80c1af7df.jpg",
          "position": 2,
          "content": "腌制牛肉，1勺料酒"
        },
        {
          "image": "https://cp1.douguo.com/upload/caiku/1/4/9/600_1481efd00424da7e42d4301eb466d369.jpg",
          "thumb": "https://cp1.douguo.com/upload/caiku/1/4/9/140_1481efd00424da7e42d4301eb466d369.jpg",
          "position": 3,
          "content": "2勺淀粉拌好腌制15分钟"
        },
        {
          "image": "https://cp1.douguo.com/upload/caiku/1/a/d/600_1ae6f6532ac6d32ef860902441ad6d3d.jpg",
          "thumb": "https://cp1.douguo.com/upload/caiku/1/a/d/140_1ae6f6532ac6d32ef860902441ad6d3d.jpg",
          "position": 4,
          "content": "1勺生抽"
        },
        {
          "image": "https://cp1.douguo.com/upload/caiku/7/e/4/600_7e1661ba526005143c01131fd9a04674.jpg",
          "thumb": "https://cp1.douguo.com/upload/caiku/7/e/4/140_7e1661ba526005143c01131fd9a04674.jpg",
          "position": 5,
          "content": "锅中烧油，油热下牛肉，用筷子搅拌"
        },
        {
          "image": "https://cp1.douguo.com/upload/caiku/2/6/9/600_26d682a6b787380730bf00c6f8e81c69.jpg",
          "thumb": "https://cp1.douguo.com/upload/caiku/2/6/9/140_26d682a6b787380730bf00c6f8e81c69.jpg",
          "position": 6,
          "content": "炒至牛肉变色，加洋葱翻炒，加半小勺盐，翻炒一分钟，再加1勺生抽"
        },
        {
          "image": "https://cp1.douguo.com/upload/caiku/6/3/8/600_632ad513ec3dbba9a5bb684af5962c28.jpg",
          "thumb": "https://cp1.douguo.com/upload/caiku/6/3/8/140_632ad513ec3dbba9a5bb684af5962c28.jpg",
          "position": 7,
          "content": "加入香菜小米辣，1小勺鸡精翻炒"
        },
        {
          "image": "https://cp1.douguo.com/upload/caiku/9/a/7/600_9aac0885ebfe0d507f964a744a253387.jpg",
          "thumb": "https://cp1.douguo.com/upload/caiku/9/a/7/140_9aac0885ebfe0d507f964a744a253387.jpg",
          "position": 8,
          "content": "翻炒1分钟关火，牛肉很嫩哦"
        },
        {
          "image": "https://cp1.douguo.com/upload/caiku/8/4/5/600_84f7f4822c0b222ee16e8a174419dc35.jpg",
          "thumb": "https://cp1.douguo.com/upload/caiku/8/4/5/140_84f7f4822c0b222ee16e8a174419dc35.jpg",
          "position": 9,
          "content": "出锅装盘，牛气冲天，火辣开年"
        }
      ]
    },
    {
      "seasoning": {},
      "image": "https://i1.douguo.com//upload/caiku/d/a/9/600_da96189ee8a604487f2da26bf729a1f9.jpeg",
      "major": [
        {
          "note": "500g",
          "title": "牛肉"
        },
        {
          "note": "2个",
          "title": "土豆"
        },
        {
          "note": "1个",
          "title": "西红柿"
        },
        {
          "note": "1块",
          "title": "姜"
        },
        {
          "note": "1段",
          "title": "葱"
        },
        {
          "note": "适量",
          "title": "大料、香叶、花椒、桂皮"
        },
        {
          "note": "3汤匙",
          "title": "味极鲜"
        },
        {
          "note": "1汤匙",
          "title": "老抽"
        },
        {
          "note": "1汤匙",
          "title": "蚝油"
        },
        {
          "note": "1汤匙",
          "title": "白酒或料酒"
        },
        {
          "note": "10g",
          "title": "盐"
        },
        {
          "note": "8颗",
          "title": "冰糖"
        },
        {
          "note": "半块",
          "title": "豆腐乳"
        }
      ],
      "cook_rate": 5,
      "dish": "土豆炖牛肉",
      "cookstep": [
        {
          "image": "https://cp1.douguo.com/upload/caiku/a/4/a/600_a4aabd3e31591af6e41d6b667330f27a.jpeg",
          "thumb": "https://cp1.douguo.com/upload/caiku/a/4/a/140_a4aabd3e31591af6e41d6b667330f27a.jpeg",
          "position": 1,
          "content": "牛肉块洗净，放入锅中，倒入冷水（一定要冷水），沒过牛肉。\n放入两片生姜、一勺料酒，水烧开后，撇去浮沫（一定要撇去浮沫，不然会很腥）。焯水两分钟左右，捞出。"
        },
        {
          "image": "https://cp1.douguo.com/upload/caiku/5/1/e/600_51fb886edb850cabcd53cebd82b2de6e.jpeg",
          "thumb": "https://cp1.douguo.com/upload/caiku/5/1/e/140_51fb886edb850cabcd53cebd82b2de6e.jpeg",
          "position": 2,
          "content": "西红柿切块；\n准备配料：大葱切段、姜切片、大料2个、花椒十粒左右、香叶1片、桂皮2块、山楂片一把。"
        },
        {
          "image": "https://cp1.douguo.com/upload/caiku/d/1/3/600_d1744bd391427cc0659382e72fb75db3.jpeg",
          "thumb": "https://cp1.douguo.com/upload/caiku/d/1/3/140_d1744bd391427cc0659382e72fb75db3.jpeg",
          "position": 3,
          "content": "锅里放比平时炒菜多一些的油，小火，炒香配料。"
        },
        {
          "image": "https://cp1.douguo.com/upload/caiku/6/3/0/600_63b7f34eec7b47d3978ca5b38589cef0.jpeg",
          "thumb": "https://cp1.douguo.com/upload/caiku/6/3/0/140_63b7f34eec7b47d3978ca5b38589cef0.jpeg",
          "position": 4,
          "content": "先倒入牛肉块，翻炒均匀，再倒入西红柿块，翻炒均匀。不要炒太久，不然牛肉容易紧。"
        },
        {
          "image": "https://cp1.douguo.com/upload/caiku/9/0/2/600_90a00cd6f451be6afc36e5bfbbc37372.jpeg",
          "thumb": "https://cp1.douguo.com/upload/caiku/9/0/2/140_90a00cd6f451be6afc36e5bfbbc37372.jpeg",
          "position": 5,
          "content": "放三汤匙味极鲜、1汤匙老抽、1汤匙蚝油、1汤匙白酒、六颗冰糖、半块豆腐乳和一点豆腐乳的汤汁，翻炒均匀。"
        },
        {
          "image": "https://cp1.douguo.com/upload/caiku/7/1/6/600_715df40644b17913b2275576e3737016.jpeg",
          "thumb": "https://cp1.douguo.com/upload/caiku/7/1/6/140_715df40644b17913b2275576e3737016.jpeg",
          "position": 6,
          "content": "加半锅热水（一定要热水），沒过牛肉。放入几瓣山楂片（山楂可以起到促进肉质软烂的作用）。\n水可以多加一些，因为炖牛肉耗时比较久。"
        },
        {
          "image": "https://cp1.douguo.com/upload/caiku/e/3/b/600_e31c89d8d474380ae1f0a35f2065da3b.jpeg",
          "thumb": "https://cp1.douguo.com/upload/caiku/e/3/b/140_e31c89d8d474380ae1f0a35f2065da3b.jpeg",
          "position": 7,
          "content": "大火炖5分钟，转中火再炖25分钟。\n加三勺盐（约10克），放入土豆块，炖15分钟，土豆基本上就炖软了。加一点香油，出锅，撒葱花即可。"
        }
      ]
    },
    {
      "seasoning": {},
      "image": "https://i1.douguo.com//upload/caiku/7/6/6/600_765058a757a51083be109d31e6bf5566.gif",
      "major": [
        {
          "note": "60克",
          "title": "牛肉末"
        },
        {
          "note": "80克",
          "title": "山药"
        },
        {
          "note": "20克",
          "title": "胡萝卜"
        },
        {
          "note": "30克",
          "title": "西蓝花"
        },
        {
          "note": "适量",
          "title": "盐"
        },
        {
          "note": "适量",
          "title": "酱油"
        },
        {
          "note": "适量",
          "title": "素蚝油"
        },
        {
          "note": "适量",
          "title": "水淀粉"
        },
        {
          "note": "适量",
          "title": "食用油"
        },
        {
          "note": "适量",
          "title": "葱花"
        },
        {
          "note": "适量",
          "title": "姜"
        }
      ],
      "cook_rate": 0,
      "dish": "【宝宝辅食】西蓝花山药炒牛肉",
      "cookstep": [
        {
          "image": "https://cp1.douguo.com/upload/caiku/7/e/0/600_7e7911ef17ae7503e08d8e6bcf789290.gif",
          "thumb": "https://cp1.douguo.com/upload/caiku/7/e/0/140_7e7911ef17ae7503e08d8e6bcf789290.gif",
          "position": 1,
          "content": "不管是牛肉还是猪肉啊，炒之前都得再腌一下。往牛肉末里加姜丝、酱油、淀粉和食用油，拌匀腌制10分钟。"
        },
        {
          "image": "https://cp1.douguo.com/upload/caiku/9/a/b/600_9ae27f6306909c999bb04aee7660ac8b.gif",
          "thumb": "https://cp1.douguo.com/upload/caiku/9/a/b/140_9ae27f6306909c999bb04aee7660ac8b.gif",
          "position": 2,
          "content": "腌好的肉末在加蔬菜一起做之前，最好是早早炒一下，炒到肉末变色备用。"
        },
        {
          "image": "https://cp1.douguo.com/upload/caiku/3/e/b/600_3ef9b194d545556809d5475c122bcccb.gif",
          "thumb": "https://cp1.douguo.com/upload/caiku/3/e/b/140_3ef9b194d545556809d5475c122bcccb.gif",
          "position": 3,
          "content": "爆锅的固定搭配，还得是葱花，翻炒出香味之后再把其他的蔬菜加进去。"
        },
        {
          "image": "https://cp1.douguo.com/upload/caiku/0/d/e/600_0d62acdf807736ccee0aecebc4dc4f3e.gif",
          "thumb": "https://cp1.douguo.com/upload/caiku/0/d/e/140_0d62acdf807736ccee0aecebc4dc4f3e.gif",
          "position": 4,
          "content": "胡萝卜丝、山药片我们家孩子接受度都比较高，加进去，翻炒到断生。"
        },
        {
          "image": "https://cp1.douguo.com/upload/caiku/5/a/a/600_5a17ced22279a2f32fea587ecb7c531a.gif",
          "thumb": "https://cp1.douguo.com/upload/caiku/5/a/a/140_5a17ced22279a2f32fea587ecb7c531a.gif",
          "position": 5,
          "content": "调味料不用太多了，盐、素蚝油加上一丢丢的清水就够了。这里的山药片，你们用铁棍山药或者是菜山药做都可以的，但一定要盖盖焖煮到山药片熟透再进行下一步。"
        },
        {
          "image": "https://cp1.douguo.com/upload/caiku/4/f/e/600_4f512ce36f18e65427899b048706ae0e.gif",
          "thumb": "https://cp1.douguo.com/upload/caiku/4/f/e/140_4f512ce36f18e65427899b048706ae0e.gif",
          "position": 6,
          "content": "西蓝花提前焯水了，也不用担心会不熟。再把炒好的肉碎扔进去，加上水淀粉收收汁。"
        },
        {
          "image": "https://cp1.douguo.com/upload/caiku/0/2/3/600_02e0cd4cf4384d505389f8c8ec20fb23.gif",
          "thumb": "https://cp1.douguo.com/upload/caiku/0/2/3/140_02e0cd4cf4384d505389f8c8ec20fb23.gif",
          "position": 7,
          "content": "因为前面的食材基本都提前处理过了也很好熟，时间不用太长，确保食材都完全熟透了就能盛出来了，直接铺到米饭上做成盖浇饭都很好吃。"
        }
      ]
    },
    {
      "seasoning": {},
      "image": "https://i1.douguo.com//upload/caiku/7/c/2/600_7c9977242179c4ad4434e2deffaf3dd2.jpeg",
      "major": [
        {
          "note": "2个",
          "title": "番茄"
        },
        {
          "note": "1个",
          "title": "土豆"
        },
        {
          "note": "",
          "title": "牛肉"
        },
        {
          "note": "2个",
          "title": "八角"
        },
        {
          "note": "可不加",
          "title": "番茄酱"
        },
        {
          "note": "",
          "title": "葱姜"
        },
        {
          "note": "",
          "title": "生抽"
        },
        {
          "note": "",
          "title": "料酒"
        },
        {
          "note": "",
          "title": "盐"
        },
        {
          "note": "",
          "title": "水淀粉"
        },
        {
          "note": "少许",
          "title": "汤"
        }
      ],
      "cook_rate": 4.8,
      "dish": "番茄土豆炖牛肉～低脂又美味",
      "cookstep": [
        {
          "image": "https://cp1.douguo.com/upload/caiku/d/4/2/600_d4edab75d40ee9fa9e61895c1a6c8a12.jpeg",
          "thumb": "https://cp1.douguo.com/upload/caiku/d/4/2/140_d4edab75d40ee9fa9e61895c1a6c8a12.jpeg",
          "position": 1,
          "content": "牛肉切块，和葱段、料酒一起下入凉水锅中，焯水，煮两分钟后捞出来冲干净，沥干备用"
        },
        {
          "image": "https://cp1.douguo.com/upload/caiku/8/6/0/600_86d8291824d402626be3076fe1d0f6a0.jpeg",
          "thumb": "https://cp1.douguo.com/upload/caiku/8/6/0/140_86d8291824d402626be3076fe1d0f6a0.jpeg",
          "position": 2,
          "content": "土豆削皮切块，放水里浸泡备用，番茄用开水烫过，去皮，切小块"
        },
        {
          "image": "https://cp1.douguo.com/upload/caiku/b/6/e/600_b6a69b32749ea29c3c0e29eea105b14e.jpeg",
          "thumb": "https://cp1.douguo.com/upload/caiku/b/6/e/140_b6a69b32749ea29c3c0e29eea105b14e.jpeg",
          "position": 3,
          "content": "加入适量清水、八角、老姜、生抽、水量要没过牛肉。大火烧开后转小火炖40分钟"
        },
        {
          "image": "https://cp1.douguo.com/upload/caiku/0/7/f/600_07fd3a727e53f30368c28b97a1aba80f.jpeg",
          "thumb": "https://cp1.douguo.com/upload/caiku/0/7/f/140_07fd3a727e53f30368c28b97a1aba80f.jpeg",
          "position": 4,
          "content": "然后放入土豆、番茄，盐、喜欢口味浓点的，可再加点番茄酱，锅中再添少量清水，大火烧开转小火炖"
        },
        {
          "image": "https://cp1.douguo.com/upload/caiku/9/f/b/600_9fe62bbd03fc16839f3fc65256d1855b.jpeg",
          "thumb": "https://cp1.douguo.com/upload/caiku/9/f/b/140_9fe62bbd03fc16839f3fc65256d1855b.jpeg",
          "position": 5,
          "content": "大概炖30分钟左右，加少量糖提鲜，将和好的水淀粉倒入，收浓汤汁，出锅即可"
        },
        {
          "image": "https://cp1.douguo.com/upload/caiku/8/6/7/600_865862548c81b0fdd804420d3cd917b7.jpeg",
          "thumb": "https://cp1.douguo.com/upload/caiku/8/6/7/140_865862548c81b0fdd804420d3cd917b7.jpeg",
          "position": 6,
          "content": "成品图～"
        }
      ]
    },
    {
      "seasoning": {},
      "image": "https://i1.douguo.com//upload/caiku/6/3/c/600_1723375250686.jpg",
      "major": [
        {
          "note": "一块",
          "title": "牛里脊"
        },
        {
          "note": "各几个",
          "title": "青红椒"
        },
        {
          "note": "一个",
          "title": "洋葱"
        },
        {
          "note": "一小块",
          "title": "姜"
        },
        {
          "note": "几瓣",
          "title": "蒜"
        },
        {
          "note": "少许",
          "title": "太太乐鸡精"
        },
        {
          "note": "少许",
          "title": "太太乐蚝油"
        },
        {
          "note": "一大勺（看你的食材多少放佐料）",
          "title": "太太乐原味鲜小炒酱油"
        },
        {
          "note": "少许",
          "title": "白糖"
        },
        {
          "note": "适量",
          "title": "生粉"
        },
        {
          "note": "炒这个牛肉丝油要多点汤匙",
          "title": "油"
        }
      ],
      "cook_rate": 0,
      "dish": "爆炒黄牛肉丝 鲜香美味 超级下饭神器",
      "cookstep": [
        {
          "image": "https://cp1.douguo.com/upload/caiku/b/1/4/600_b11fc778731eaaf2d7ebc03c5f2a9bd4.jpeg",
          "thumb": "https://cp1.douguo.com/upload/caiku/b/1/4/140_b11fc778731eaaf2d7ebc03c5f2a9bd4.jpeg",
          "position": 1,
          "content": "所有食材准备好  牛肉丝切好腌制 放少许太太乐减盐蚝油 太太乐原味鲜小炒鲜良造酱油  太太乐鸡精少许 白糖 白胡椒粉 生粉拌均匀腌制 在加少许油锁住水分备用"
        },
        {
          "image": "https://cp1.douguo.com/upload/caiku/0/9/3/600_0936455e924914a2aa0f30ee33751853.jpeg",
          "thumb": "https://cp1.douguo.com/upload/caiku/0/9/3/140_0936455e924914a2aa0f30ee33751853.jpeg",
          "position": 2,
          "content": "锅中放入适量的油 边炒蒜香味 把腌好的牛肉丝放入锅中大火翻炒 快速出锅称出备用 在放少许油 炒青红椒丝 洋葱丝"
        },
        {
          "image": "https://cp1.douguo.com/upload/caiku/d/1/7/600_d105a7a5067d12154ac905ddbf86d567.jpeg",
          "thumb": "https://cp1.douguo.com/upload/caiku/d/1/7/140_d105a7a5067d12154ac905ddbf86d567.jpeg",
          "position": 3,
          "content": "在放少许太太乐原味鲜小炒鲜酿造酱油"
        },
        {
          "image": "https://cp1.douguo.com/upload/caiku/b/1/e/600_b15bfa9258658d0cf13d971fb6dd637e.jpeg",
          "thumb": "https://cp1.douguo.com/upload/caiku/b/1/e/140_b15bfa9258658d0cf13d971fb6dd637e.jpeg",
          "position": 4,
          "content": "大火翻炒片刻"
        },
        {
          "image": "https://cp1.douguo.com/upload/caiku/e/6/5/600_e6082aa6494c63c92346f705d5a66425.jpeg",
          "thumb": "https://cp1.douguo.com/upload/caiku/e/6/5/140_e6082aa6494c63c92346f705d5a66425.jpeg",
          "position": 5,
          "content": "加入先前炒好的牛肉丝"
        },
        {
          "image": "https://cp1.douguo.com/upload/caiku/a/9/a/600_a909e846f32a30fee5b3b96068914a4a.jpeg",
          "thumb": "https://cp1.douguo.com/upload/caiku/a/9/a/140_a909e846f32a30fee5b3b96068914a4a.jpeg",
          "position": 6,
          "content": "在少许太太乐鸡精调味即可"
        },
        {
          "image": "https://cp1.douguo.com/upload/caiku/6/4/a/600_642d44d6a2d292a3b6806cd43489000a.jpeg",
          "thumb": "https://cp1.douguo.com/upload/caiku/6/4/a/140_642d44d6a2d292a3b6806cd43489000a.jpeg",
          "position": 7,
          "content": "拌均匀 出锅了"
        },
        {
          "image": "https://cp1.douguo.com/upload/caiku/6/3/4/600_639d86adb886d59ead095a476bc59034.jpeg",
          "thumb": "https://cp1.douguo.com/upload/caiku/6/3/4/140_639d86adb886d59ead095a476bc59034.jpeg",
          "position": 8,
          "content": "开吃啦！！！"
        },
        {
          "image": "https://cp1.douguo.com/upload/caiku/3/6/8/600_365d126ae11bf32ac65dd8997b756638.jpeg",
          "thumb": "https://cp1.douguo.com/upload/caiku/3/6/8/140_365d126ae11bf32ac65dd8997b756638.jpeg",
          "position": 9,
          "content": "超级美味"
        },
        {
          "image": "https://cp1.douguo.com/upload/caiku/1/3/f/600_138320e5f6a4c661d50a30ecdf84284f.jpeg",
          "thumb": "https://cp1.douguo.com/upload/caiku/1/3/f/140_138320e5f6a4c661d50a30ecdf84284f.jpeg",
          "position": 10,
          "content": "成品图"
        }
      ]
    },
    {
      "seasoning": {},
      "image": "https://i1.douguo.com//upload/caiku/c/3/d/600_1697876958310.jpg",
      "major": [
        {
          "note": "200克",
          "title": "牛肉"
        },
        {
          "note": "300克",
          "title": "洋葱"
        },
        {
          "note": "60克",
          "title": "胡萝卜"
        },
        {
          "note": "20克",
          "title": "葱白"
        },
        {
          "note": "15克",
          "title": "葱花"
        }
      ],
      "cook_rate": 5,
      "dish": " 洋葱炒牛肉",
      "cookstep": [
        {
          "image": "https://cp1.douguo.com/upload/caiku/a/1/f/600_a19051b003f531437b89328c5a53325f.jpeg",
          "thumb": "https://cp1.douguo.com/upload/caiku/a/1/f/140_a19051b003f531437b89328c5a53325f.jpeg",
          "position": 1,
          "content": "腌制牛肉"
        },
        {
          "image": "https://cp1.douguo.com/upload/caiku/c/8/5/600_c83f55fc98c7ebfb18a79dcedc4a3395.jpeg",
          "thumb": "https://cp1.douguo.com/upload/caiku/c/8/5/140_c83f55fc98c7ebfb18a79dcedc4a3395.jpeg",
          "position": 2,
          "content": "炒熟牛肉"
        },
        {
          "image": "https://cp1.douguo.com/upload/caiku/8/9/2/600_891c4087c2c1929cfd5b1a8c12f53272.jpeg",
          "thumb": "https://cp1.douguo.com/upload/caiku/8/9/2/140_891c4087c2c1929cfd5b1a8c12f53272.jpeg",
          "position": 3,
          "content": "炒香配菜"
        },
        {
          "image": "https://cp1.douguo.com/upload/caiku/3/6/a/600_3662cef9081e9891da8c89c99a68e60a.jpeg",
          "thumb": "https://cp1.douguo.com/upload/caiku/3/6/a/140_3662cef9081e9891da8c89c99a68e60a.jpeg",
          "position": 4,
          "content": "准备调味"
        },
        {
          "image": "https://cp1.douguo.com/upload/caiku/c/c/5/600_cc1edd002cc8d27ca0172ea6884c4a05.jpeg",
          "thumb": "https://cp1.douguo.com/upload/caiku/c/c/5/140_cc1edd002cc8d27ca0172ea6884c4a05.jpeg",
          "position": 5,
          "content": "完成调味"
        },
        {
          "image": "https://cp1.douguo.com/upload/caiku/5/1/d/600_51d0bbb4a74c26f77d6087a09913371d.jpeg",
          "thumb": "https://cp1.douguo.com/upload/caiku/5/1/d/140_51d0bbb4a74c26f77d6087a09913371d.jpeg",
          "position": 6,
          "content": "提香润色开吃！"
        }
      ]
    }
  ]
}